pauli_lcu_module.cpython-39-darwin.so
pauli_lcu/tools.py
pauli_lcu/__init__.py
pauli_lcu/decomposition.py
pauli_lcu-1.0.1.dist-info/RECORD
pauli_lcu-1.0.1.dist-info/WHEEL
pauli_lcu-1.0.1.dist-info/top_level.txt
pauli_lcu-1.0.1.dist-info/METADATA
pauli_lcu-1.0.1.dist-info/licenses/LICENSE
