Metadata-Version: 2.4
Name: pauli_lcu
Version: 1.0.1
Summary: Decomposition of a matrix into Pauli strings
Author-email: Aleksei Ivanov <aleksei.ivanov@riverlane.com>, Christoph Sunderhauf <christoph.sunderhauf@riverlane.com>
Classifier: Programming Language :: Python :: 3
Requires-Python: >=3.9
License-File: LICENSE
Requires-Dist: numpy
Requires-Dist: pytest
Dynamic: license-file
